setup.py
quirc/__init__.py
quirc/base.py
quirc/compat.py
quirc/converters.py
quirc.egg-info/PKG-INFO
quirc.egg-info/SOURCES.txt
quirc.egg-info/dependency_links.txt
quirc.egg-info/top_level.txt
quirc/api/__init__.py
quirc/api/constants.py
quirc/api/exceptions.py
quirc/api/functions.py
quirc/api/structures.py